Workbook

Sheet How to use
A1: THIS IS A VIEW-ONLY EXCEL SHEET.
A2: DOWNLOAD THIS SHEET (FILE -> DOWNLOAD AS XLSX) AND THEN USE IT ON YOUR OWN
A4: This sheet has been prepared by Ankur Warikoo, who is NOT a financial advisor :)
A5: So use this sheet with your judgement and not like "this is my final decision"
A7: All cells in green are input cells, which means you have to put in the number
A8: All other cells - ideally you should not touch them. But I have kept them open, so that you can see the formula and how it works
A10: NOTE:
A11: Since I am not a financial advisor, there could be some errors in the sheet. If there are, send me an email and I will fix them. Simple :)
A13: Hope you find this useful.

Sheet Pay off vs Invest
A1: Loan Amount remaining | B1: 1000000
A2: Loan Interest Rate | B2: 0.08
A3: Current month of the loan | B3: 15
A4: Months remaining for the loan | B4: 60
A5: Lumpsum amount you have? | B5: 100000
A6: Amount you can invest every month? | B6: 7000
A7: Return you can generate every year? | B7: 0.1
A9: Over the tenure of your loan
A10: You will pay interest of: | B10: =-CUMIPMT(B2/12,(B3+B4),B1,B3,B4,1) -> 172862.51
A11: You would have invested: | B11: =B5+B6*B4 -> 520000
A12: Your investment would have grown to: | B12: =-FV(B7/12,B4,B6,B5) -> 706590.4
A13: Which means you made an excess of: | B13: =B12-B11 -> 186590.4
A14: This means you should | B14: =IF(B13<B10,"PAY OFF THE LOAN", "INVEST THE AMOUNT") -> INVEST THE AMOUNT

Sheet Calculations
A1: Month | B1: Amount | C1: Return | D1: Total Amount | E1: Inflation adjusted | F1: Total Amount | H1: Lumpsum | I1: Inflation adjusted
A2: 1 | B2: ='Pay off vs Invest'!B6 -> 7000 | C2: =IF(A2<=('Pay off vs Invest'!$B$2-'Pay off vs Invest'!$B$1)*12,Calculations!B2*(1+#REF!/12)^(('Pay off vs Invest'!$B$2-'Pay off vs Invest'!$B$1)*12-A2),0) -> 0 | D2: =SUM(C2:C481) -> 0 | E2: =C2/((1+#REF!/12)^((('Pay off vs Invest'!$B$2-'Pay off vs Invest'!$B$1)*12)-Calculations!A2)) -> #REF! | F2: =SUM(E2:E481) -> #REF! | H2: ='Pay off vs Invest'!B4*(1+#REF!)^(('Pay off vs Invest'!B2-'Pay off vs Invest'!B1)) -> #REF! | I2: =H2/(1+#REF!)^('Pay off vs Invest'!B2-'Pay off vs Invest'!B1) -> #REF!
A3: =A2+1 -> 2 | B3: =B2 -> 7000 | C3: =IF(A3<=('Pay off vs Invest'!$B$2-'Pay off vs Invest'!$B$1)*12,Calculations!B3*(1+#REF!/12)^(('Pay off vs Invest'!$B$2-'Pay off vs Invest'!$B$1)*12-A3),0) -> 0 | E3: =C3/((1+#REF!/12)^((('Pay off vs Invest'!$B$2-'Pay off vs Invest'!$B$1)*12)-Calculations!A3)) -> #REF!
A4: =A3+1 -> 3 | B4: =B3 -> 7000 | C4: =IF(A4<=('Pay off vs Invest'!$B$2-'Pay off vs Invest'!$B$1)*12,Calculations!B4*(1+#REF!/12)^(('Pay off vs Invest'!$B$2-'Pay off vs Invest'!$B$1)*12-A4),0) -> 0 | E4: =C4/((1+#REF!/12)^((('Pay off vs Invest'!$B$2-'Pay off vs Invest'!$B$1)*12)-Calculations!A4)) -> #REF!
A5: =A4+1 -> 4 | B5: =B4 -> 7000 | C5: =IF(A5<=('Pay off vs Invest'!$B$2-'Pay off vs Invest'!$B$1)*12,Calculations!B5*(1+#REF!/12)^(('Pay off vs Invest'!$B$2-'Pay off vs Invest'!$B$1)*12-A5),0) -> 0 | E5: =C5/((1+#REF!/12)^((('Pay off vs Invest'!$B$2-'Pay off vs Invest'!$B$1)*12)-Calculations!A5)) -> #REF!
A6: =A5+1 -> 5 | B6: =B5 -> 7000 | C6: =IF(A6<=('Pay off vs Invest'!$B$2-'Pay off vs Invest'!$B$1)*12,Calculations!B6*(1+#REF!/12)^(('Pay off vs Invest'!$B$2-'Pay off vs Invest'!$B$1)*12-A6),0) -> 0 | E6: =C6/((1+#REF!/12)^((('Pay off vs Invest'!$B$2-'Pay off vs Invest'!$B$1)*12)-Calculations!A6)) -> #REF!
A7: =A6+1 -> 6 | B7: =B6 -> 7000 | C7: =IF(A7<=('Pay off vs Invest'!$B$2-'Pay off vs Invest'!$B$1)*12,Calculations!B7*(1+#REF!/12)^(('Pay off vs Invest'!$B$2-'Pay off vs Invest'!$B$1)*12-A7),0) -> 0 | E7: =C7/((1+#REF!/12)^((('Pay off vs Invest'!$B$2-'Pay off vs Invest'!$B$1)*12)-Calculations!A7)) -> #REF!
A8: =A7+1 -> 7 | B8: =B7 -> 7000 | C8: =IF(A8<=('Pay off vs Invest'!$B$2-'Pay off vs Invest'!$B$1)*12,Calculations!B8*(1+#REF!/12)^(('Pay off vs Invest'!$B$2-'Pay off vs Invest'!$B$1)*12-A8),0) -> 0 | E8: =C8/((1+#REF!/12)^((('Pay off vs Invest'!$B$2-'Pay off vs Invest'!$B$1)*12)-Calculations!A8)) -> #REF!
A9: =A8+1 -> 8 | B9: =B8 -> 7000 | C9: =IF(A9<=('Pay off vs Invest'!$B$2-'Pay off vs Invest'!$B$1)*12,Calculations!B9*(1+#REF!/12)^(('Pay off vs Invest'!$B$2-'Pay off vs Invest'!$B$1)*12-A9),0) -> 0 | E9: =C9/((1+#REF!/12)^((('Pay off vs Invest'!$B$2-'Pay off vs Invest'!$B$1)*12)-Calculations!A9)) -> #REF!
A10: =A9+1 -> 9 | B10: =B9 -> 7000 | C10: =IF(A10<=('Pay off vs Invest'!$B$2-'Pay off vs Invest'!$B$1)*12,Calculations!B10*(1+#REF!/12)^(('Pay off vs Invest'!$B$2-'Pay off vs Invest'!$B$1)*12-A10),0) -> 0 | E10: =C10/((1+#REF!/12)^((('Pay off vs Invest'!$B$2-'Pay off vs Invest'!$B$1)*12)-Calculations!A10)) -> #REF!
A11: =A10+1 -> 10 | B11: =B10 -> 7000 | C11: =IF(A11<=('Pay off vs Invest'!$B$2-'Pay off vs Invest'!$B$1)*12,Calculations!B11*(1+#REF!/12)^(('Pay off vs Invest'!$B$2-'Pay off vs Invest'!$B$1)*12-A11),0) -> 0 | E11: =C11/((1+#REF!/12)^((('Pay off vs Invest'!$B$2-'Pay off vs Invest'!$B$1)*12)-Calculations!A11)) -> #REF!
A12: =A11+1 -> 11 | B12: =B11 -> 7000 | C12: =IF(A12<=('Pay off vs Invest'!$B$2-'Pay off vs Invest'!$B$1)*12,Calculations!B12*(1+#REF!/12)^(('Pay off vs Invest'!$B$2-'Pay off vs Invest'!$B$1)*12-A12),0) -> 0 | E12: =C12/((1+#REF!/12)^((('Pay off vs Invest'!$B$2-'Pay off vs Invest'!$B$1)*12)-Calculations!A12)) -> #REF!
A13: =A12+1 -> 12 | B13: =B12 -> 7000 | C13: =IF(A13<=('Pay off vs Invest'!$B$2-'Pay off vs Invest'!$B$1)*12,Calculations!B13*(1+#REF!/12)^(('Pay off vs Invest'!$B$2-'Pay off vs Invest'!$B$1)*12-A13),0) -> 0 | E13: =C13/((1+#REF!/12)^((('Pay off vs Invest'!$B$2-'Pay off vs Invest'!$B$1)*12)-Calculations!A13)) -> #REF!
A14: =A13+1 -> 13 | B14: =B13*(1+'Pay off vs Invest'!$B$7) -> 7700 | C14: =IF(A14<=('Pay off vs Invest'!$B$2-'Pay off vs Invest'!$B$1)*12,Calculations!B14*(1+#REF!/12)^(('Pay off vs Invest'!$B$2-'Pay off vs Invest'!$B$1)*12-A14),0) -> 0 | E14: =C14/((1+#REF!/12)^((('Pay off vs Invest'!$B$2-'Pay off vs Invest'!$B$1)*12)-Calculations!A14)) -> #REF!
A15: =A14+1 -> 14 | B15: =B14 -> 7700 | C15: =IF(A15<=('Pay off vs Invest'!$B$2-'Pay off vs Invest'!$B$1)*12,Calculations!B15*(1+#REF!/12)^(('Pay off vs Invest'!$B$2-'Pay off vs Invest'!$B$1)*12-A15),0) -> 0 | E15: =C15/((1+#REF!/12)^((('Pay off vs Invest'!$B$2-'Pay off vs Invest'!$B$1)*12)-Calculations!A15)) -> #REF!
A16: =A15+1 -> 15 | B16: =B15 -> 7700 | C16: =IF(A16<=('Pay off vs Invest'!$B$2-'Pay off vs Invest'!$B$1)*12,Calculations!B16*(1+#REF!/12)^(('Pay off vs Invest'!$B$2-'Pay off vs Invest'!$B$1)*12-A16),0) -> 0 | E16: =C16/((1+#REF!/12)^((('Pay off vs Invest'!$B$2-'Pay off vs Invest'!$B$1)*12)-Calculations!A16)) -> #REF!
A17: =A16+1 -> 16 | B17: =B16 -> 7700 | C17: =IF(A17<=('Pay off vs Invest'!$B$2-'Pay off vs Invest'!$B$1)*12,Calculations!B17*(1+#REF!/12)^(('Pay off vs Invest'!$B$2-'Pay off vs Invest'!$B$1)*12-A17),0) -> 0 | E17: =C17/((1+#REF!/12)^((('Pay off vs Invest'!$B$2-'Pay off vs Invest'!$B$1)*12)-Calculations!A17)) -> #REF!
A18: =A17+1 -> 17 | B18: =B17 -> 7700 | C18: =IF(A18<=('Pay off vs Invest'!$B$2-'Pay off vs Invest'!$B$1)*12,Calculations!B18*(1+#REF!/12)^(('Pay off vs Invest'!$B$2-'Pay off vs Invest'!$B$1)*12-A18),0) -> 0 | E18: =C18/((1+#REF!/12)^((('Pay off vs Invest'!$B$2-'Pay off vs Invest'!$B$1)*12)-Calculations!A18)) -> #REF!
A19: =A18+1 -> 18 | B19: =B18 -> 7700 | C19: =IF(A19<=('Pay off vs Invest'!$B$2-'Pay off vs Invest'!$B$1)*12,Calculations!B19*(1+#REF!/12)^(('Pay off vs Invest'!$B$2-'Pay off vs Invest'!$B$1)*12-A19),0) -> 0 | E19: =C19/((1+#REF!/12)^((('Pay off vs Invest'!$B$2-'Pay off vs Invest'!$B$1)*12)-Calculations!A19)) -> #REF!
A20: =A19+1 -> 19 | B20: =B19 -> 7700 | C20: =IF(A20<=('Pay off vs Invest'!$B$2-'Pay off vs Invest'!$B$1)*12,Calculations!B20*(1+#REF!/12)^(('Pay off vs Invest'!$B$2-'Pay off vs Invest'!$B$1)*12-A20),0) -> 0 | E20: =C20/((1+#REF!/12)^((('Pay off vs Invest'!$B$2-'Pay off vs Invest'!$B$1)*12)-Calculations!A20)) -> #REF!
A21: =A20+1 -> 20 | B21: =B20 -> 7700 | C21: =IF(A21<=('Pay off vs Invest'!$B$2-'Pay off vs Invest'!$B$1)*12,Calculations!B21*(1+#REF!/12)^(('Pay off vs Invest'!$B$2-'Pay off vs Invest'!$B$1)*12-A21),0) -> 0 | E21: =C21/((1+#REF!/12)^((('Pay off vs Invest'!$B$2-'Pay off vs Invest'!$B$1)*12)-Calculations!A21)) -> #REF!
A22: =A21+1 -> 21 | B22: =B21 -> 7700 | C22: =IF(A22<=('Pay off vs Invest'!$B$2-'Pay off vs Invest'!$B$1)*12,Calculations!B22*(1+#REF!/12)^(('Pay off vs Invest'!$B$2-'Pay off vs Invest'!$B$1)*12-A22),0) -> 0 | E22: =C22/((1+#REF!/12)^((('Pay off vs Invest'!$B$2-'Pay off vs Invest'!$B$1)*12)-Calculations!A22)) -> #REF!
A23: =A22+1 -> 22 | B23: =B22 -> 7700 | C23: =IF(A23<=('Pay off vs Invest'!$B$2-'Pay off vs Invest'!$B$1)*12,Calculations!B23*(1+#REF!/12)^(('Pay off vs Invest'!$B$2-'Pay off vs Invest'!$B$1)*12-A23),0) -> 0 | E23: =C23/((1+#REF!/12)^((('Pay off vs Invest'!$B$2-'Pay off vs Invest'!$B$1)*12)-Calculations!A23)) -> #REF!
A24: =A23+1 -> 23 | B24: =B23 -> 7700 | C24: =IF(A24<=('Pay off vs Invest'!$B$2-'Pay off vs Invest'!$B$1)*12,Calculations!B24*(1+#REF!/12)^(('Pay off vs Invest'!$B$2-'Pay off vs Invest'!$B$1)*12-A24),0) -> 0 | E24: =C24/((1+#REF!/12)^((('Pay off vs Invest'!$B$2-'Pay off vs Invest'!$B$1)*12)-Calculations!A24)) -> #REF!
A25: =A24+1 -> 24 | B25: =B24 -> 7700 | C25: =IF(A25<=('Pay off vs Invest'!$B$2-'Pay off vs Invest'!$B$1)*12,Calculations!B25*(1+#REF!/12)^(('Pay off vs Invest'!$B$2-'Pay off vs Invest'!$B$1)*12-A25),0) -> 0 | E25: =C25/((1+#REF!/12)^((('Pay off vs Invest'!$B$2-'Pay off vs Invest'!$B$1)*12)-Calculations!A25)) -> #REF!
A26: =A25+1 -> 25 | B26: =B25*(1+'Pay off vs Invest'!$B$7) -> 8470 | C26: =IF(A26<=('Pay off vs Invest'!$B$2-'Pay off vs Invest'!$B$1)*12,Calculations!B26*(1+#REF!/12)^(('Pay off vs Invest'!$B$2-'Pay off vs Invest'!$B$1)*12-A26),0) -> 0 | E26: =C26/((1+#REF!/12)^((('Pay off vs Invest'!$B$2-'Pay off vs Invest'!$B$1)*12)-Calculations!A26)) -> #REF!
A27: =A26+1 -> 26 | B27: =B26 -> 8470 | C27: =IF(A27<=('Pay off vs Invest'!$B$2-'Pay off vs Invest'!$B$1)*12,Calculations!B27*(1+#REF!/12)^(('Pay off vs Invest'!$B$2-'Pay off vs Invest'!$B$1)*12-A27),0) -> 0 | E27: =C27/((1+#REF!/12)^((('Pay off vs Invest'!$B$2-'Pay off vs Invest'!$B$1)*12)-Calculations!A27)) -> #REF!
A28: =A27+1 -> 27 | B28: =B27 -> 8470 | C28: =IF(A28<=('Pay off vs Invest'!$B$2-'Pay off vs Invest'!$B$1)*12,Calculations!B28*(1+#REF!/12)^(('Pay off vs Invest'!$B$2-'Pay off vs Invest'!$B$1)*12-A28),0) -> 0 | E28: =C28/((1+#REF!/12)^((('Pay off vs Invest'!$B$2-'Pay off vs Invest'!$B$1)*12)-Calculations!A28)) -> #REF!
A29: =A28+1 -> 28 | B29: =B28 -> 8470 | C29: =IF(A29<=('Pay off vs Invest'!$B$2-'Pay off vs Invest'!$B$1)*12,Calculations!B29*(1+#REF!/12)^(('Pay off vs Invest'!$B$2-'Pay off vs Invest'!$B$1)*12-A29),0) -> 0 | E29: =C29/((1+#REF!/12)^((('Pay off vs Invest'!$B$2-'Pay off vs Invest'!$B$1)*12)-Calculations!A29)) -> #REF!
A30: =A29+1 -> 29 | B30: =B29 -> 8470 | C30: =IF(A30<=('Pay off vs Invest'!$B$2-'Pay off vs Invest'!$B$1)*12,Calculations!B30*(1+#REF!/12)^(('Pay off vs Invest'!$B$2-'Pay off vs Invest'!$B$1)*12-A30),0) -> 0 | E30: =C30/((1+#REF!/12)^((('Pay off vs Invest'!$B$2-'Pay off vs Invest'!$B$1)*12)-Calculations!A30)) -> #REF!
A31: =A30+1 -> 30 | B31: =B30 -> 8470 | C31: =IF(A31<=('Pay off vs Invest'!$B$2-'Pay off vs Invest'!$B$1)*12,Calculations!B31*(1+#REF!/12)^(('Pay off vs Invest'!$B$2-'Pay off vs Invest'!$B$1)*12-A31),0) -> 0 | E31: =C31/((1+#REF!/12)^((('Pay off vs Invest'!$B$2-'Pay off vs Invest'!$B$1)*12)-Calculations!A31)) -> #REF!
A32: =A31+1 -> 31 | B32: =B31 -> 8470 | C32: =IF(A32<=('Pay off vs Invest'!$B$2-'Pay off vs Invest'!$B$1)*12,Calculations!B32*(1+#REF!/12)^(('Pay off vs Invest'!$B$2-'Pay off vs Invest'!$B$1)*12-A32),0) -> 0 | E32: =C32/((1+#REF!/12)^((('Pay off vs Invest'!$B$2-'Pay off vs Invest'!$B$1)*12)-Calculations!A32)) -> #REF!
A33: =A32+1 -> 32 | B33: =B32 -> 8470 | C33: =IF(A33<=('Pay off vs Invest'!$B$2-'Pay off vs Invest'!$B$1)*12,Calculations!B33*(1+#REF!/12)^(('Pay off vs Invest'!$B$2-'Pay off vs Invest'!$B$1)*12-A33),0) -> 0 | E33: =C33/((1+#REF!/12)^((('Pay off vs Invest'!$B$2-'Pay off vs Invest'!$B$1)*12)-Calculations!A33)) -> #REF!
A34: =A33+1 -> 33 | B34: =B33 -> 8470 | C34: =IF(A34<=('Pay off vs Invest'!$B$2-'Pay off vs Invest'!$B$1)*12,Calculations!B34*(1+#REF!/12)^(('Pay off vs Invest'!$B$2-'Pay off vs Invest'!$B$1)*12-A34),0) -> 0 | E34: =C34/((1+#REF!/12)^((('Pay off vs Invest'!$B$2-'Pay off vs Invest'!$B$1)*12)-Calculations!A34)) -> #REF!
A35: =A34+1 -> 34 | B35: =B34 -> 8470 | C35: =IF(A35<=('Pay off vs Invest'!$B$2-'Pay off vs Invest'!$B$1)*12,Calculations!B35*(1+#REF!/12)^(('Pay off vs Invest'!$B$2-'Pay off vs Invest'!$B$1)*12-A35),0) -> 0 | E35: =C35/((1+#REF!/12)^((('Pay off vs Invest'!$B$2-'Pay off vs Invest'!$B$1)*12)-Calculations!A35)) -> #REF!
A36: =A35+1 -> 35 | B36: =B35 -> 8470 | C36: =IF(A36<=('Pay off vs Invest'!$B$2-'Pay off vs Invest'!$B$1)*12,Calculations!B36*(1+#REF!/12)^(('Pay off vs Invest'!$B$2-'Pay off vs Invest'!$B$1)*12-A36),0) -> 0 | E36: =C36/((1+#REF!/12)^((('Pay off vs Invest'!$B$2-'Pay off vs Invest'!$B$1)*12)-Calculations!A36)) -> #REF!
A37: =A36+1 -> 36 | B37: =B36 -> 8470 | C37: =IF(A37<=('Pay off vs Invest'!$B$2-'Pay off vs Invest'!$B$1)*12,Calculations!B37*(1+#REF!/12)^(('Pay off vs Invest'!$B$2-'Pay off vs Invest'!$B$1)*12-A37),0) -> 0 | E37: =C37/((1+#REF!/12)^((('Pay off vs Invest'!$B$2-'Pay off vs Invest'!$B$1)*12)-Calculations!A37)) -> #REF!
A38: =A37+1 -> 37 | B38: =B37*(1+'Pay off vs Invest'!$B$7) -> 9317 | C38: =IF(A38<=('Pay off vs Invest'!$B$2-'Pay off vs Invest'!$B$1)*12,Calculations!B38*(1+#REF!/12)^(('Pay off vs Invest'!$B$2-'Pay off vs Invest'!$B$1)*12-A38),0) -> 0 | E38: =C38/((1+#REF!/12)^((('Pay off vs Invest'!$B$2-'Pay off vs Invest'!$B$1)*12)-Calculations!A38)) -> #REF!
A39: =A38+1 -> 38 | B39: =B38 -> 9317 | C39: =IF(A39<=('Pay off vs Invest'!$B$2-'Pay off vs Invest'!$B$1)*12,Calculations!B39*(1+#REF!/12)^(('Pay off vs Invest'!$B$2-'Pay off vs Invest'!$B$1)*12-A39),0) -> 0 | E39: =C39/((1+#REF!/12)^((('Pay off vs Invest'!$B$2-'Pay off vs Invest'!$B$1)*12)-Calculations!A39)) -> #REF!
A40: =A39+1 -> 39 | B40: =B39 -> 9317 | C40: =IF(A40<=('Pay off vs Invest'!$B$2-'Pay off vs Invest'!$B$1)*12,Calculations!B40*(1+#REF!/12)^(('Pay off vs Invest'!$B$2-'Pay off vs Invest'!$B$1)*12-A40),0) -> 0 | E40: =C40/((1+#REF!/12)^((('Pay off vs Invest'!$B$2-'Pay off vs Invest'!$B$1)*12)-Calculations!A40)) -> #REF!
A41: =A40+1 -> 40 | B41: =B40 -> 9317 | C41: =IF(A41<=('Pay off vs Invest'!$B$2-'Pay off vs Invest'!$B$1)*12,Calculations!B41*(1+#REF!/12)^(('Pay off vs Invest'!$B$2-'Pay off vs Invest'!$B$1)*12-A41),0) -> 0 | E41: =C41/((1+#REF!/12)^((('Pay off vs Invest'!$B$2-'Pay off vs Invest'!$B$1)*12)-Calculations!A41)) -> #REF!
A42: =A41+1 -> 41 | B42: =B41 -> 9317 | C42: =IF(A42<=('Pay off vs Invest'!$B$2-'Pay off vs Invest'!$B$1)*12,Calculations!B42*(1+#REF!/12)^(('Pay off vs Invest'!$B$2-'Pay off vs Invest'!$B$1)*12-A42),0) -> 0 | E42: =C42/((1+#REF!/12)^((('Pay off vs Invest'!$B$2-'Pay off vs Invest'!$B$1)*12)-Calculations!A42)) -> #REF!
A43: =A42+1 -> 42 | B43: =B42 -> 9317 | C43: =IF(A43<=('Pay off vs Invest'!$B$2-'Pay off vs Invest'!$B$1)*12,Calculations!B43*(1+#REF!/12)^(('Pay off vs Invest'!$B$2-'Pay off vs Invest'!$B$1)*12-A43),0) -> 0 | E43: =C43/((1+#REF!/12)^((('Pay off vs Invest'!$B$2-'Pay off vs Invest'!$B$1)*12)-Calculations!A43)) -> #REF!
A44: =A43+1 -> 43 | B44: =B43 -> 9317 | C44: =IF(A44<=('Pay off vs Invest'!$B$2-'Pay off vs Invest'!$B$1)*12,Calculations!B44*(1+#REF!/12)^(('Pay off vs Invest'!$B$2-'Pay off vs Invest'!$B$1)*12-A44),0) -> 0 | E44: =C44/((1+#REF!/12)^((('Pay off vs Invest'!$B$2-'Pay off vs Invest'!$B$1)*12)-Calculations!A44)) -> #REF!
A45: =A44+1 -> 44 | B45: =B44 -> 9317 | C45: =IF(A45<=('Pay off vs Invest'!$B$2-'Pay off vs Invest'!$B$1)*12,Calculations!B45*(1+#REF!/12)^(('Pay off vs Invest'!$B$2-'Pay off vs Invest'!$B$1)*12-A45),0) -> 0 | E45: =C45/((1+#REF!/12)^((('Pay off vs Invest'!$B$2-'Pay off vs Invest'!$B$1)*12)-Calculations!A45)) -> #REF!
A46: =A45+1 -> 45 | B46: =B45 -> 9317 | C46: =IF(A46<=('Pay off vs Invest'!$B$2-'Pay off vs Invest'!$B$1)*12,Calculations!B46*(1+#REF!/12)^(('Pay off vs Invest'!$B$2-'Pay off vs Invest'!$B$1)*12-A46),0) -> 0 | E46: =C46/((1+#REF!/12)^((('Pay off vs Invest'!$B$2-'Pay off vs Invest'!$B$1)*12)-Calculations!A46)) -> #REF!
A47: =A46+1 -> 46 | B47: =B46 -> 9317 | C47: =IF(A47<=('Pay off vs Invest'!$B$2-'Pay off vs Invest'!$B$1)*12,Calculations!B47*(1+#REF!/12)^(('Pay off vs Invest'!$B$2-'Pay off vs Invest'!$B$1)*12-A47),0) -> 0 | E47: =C47/((1+#REF!/12)^((('Pay off vs Invest'!$B$2-'Pay off vs Invest'!$B$1)*12)-Calculations!A47)) -> #REF!
A48: =A47+1 -> 47 | B48: =B47 -> 9317 | C48: =IF(A48<=('Pay off vs Invest'!$B$2-'Pay off vs Invest'!$B$1)*12,Calculations!B48*(1+#REF!/12)^(('Pay off vs Invest'!$B$2-'Pay off vs Invest'!$B$1)*12-A48),0) -> 0 | E48: =C48/((1+#REF!/12)^((('Pay off vs Invest'!$B$2-'Pay off vs Invest'!$B$1)*12)-Calculations!A48)) -> #REF!
A49: =A48+1 -> 48 | B49: =B48 -> 9317 | C49: =IF(A49<=('Pay off vs Invest'!$B$2-'Pay off vs Invest'!$B$1)*12,Calculations!B49*(1+#REF!/12)^(('Pay off vs Invest'!$B$2-'Pay off vs Invest'!$B$1)*12-A49),0) -> 0 | E49: =C49/((1+#REF!/12)^((('Pay off vs Invest'!$B$2-'Pay off vs Invest'!$B$1)*12)-Calculations!A49)) -> #REF!
A50: =A49+1 -> 49 | B50: =B49*(1+'Pay off vs Invest'!$B$7) -> 10248.7 | C50: =IF(A50<=('Pay off vs Invest'!$B$2-'Pay off vs Invest'!$B$1)*12,Calculations!B50*(1+#REF!/12)^(('Pay off vs Invest'!$B$2-'Pay off vs Invest'!$B$1)*12-A50),0) -> 0 | E50: =C50/((1+#REF!/12)^((('Pay off vs Invest'!$B$2-'Pay off vs Invest'!$B$1)*12)-Calculations!A50)) -> #REF!
A51: =A50+1 -> 50 | B51: =B50 -> 10248.7 | C51: =IF(A51<=('Pay off vs Invest'!$B$2-'Pay off vs Invest'!$B$1)*12,Calculations!B51*(1+#REF!/12)^(('Pay off vs Invest'!$B$2-'Pay off vs Invest'!$B$1)*12-A51),0) -> 0 | E51: =C51/((1+#REF!/12)^((('Pay off vs Invest'!$B$2-'Pay off vs Invest'!$B$1)*12)-Calculations!A51)) -> #REF!
A52: =A51+1 -> 51 | B52: =B51 -> 10248.7 | C52: =IF(A52<=('Pay off vs Invest'!$B$2-'Pay off vs Invest'!$B$1)*12,Calculations!B52*(1+#REF!/12)^(('Pay off vs Invest'!$B$2-'Pay off vs Invest'!$B$1)*12-A52),0) -> 0 | E52: =C52/((1+#REF!/12)^((('Pay off vs Invest'!$B$2-'Pay off vs Invest'!$B$1)*12)-Calculations!A52)) -> #REF!
A53: =A52+1 -> 52 | B53: =B52 -> 10248.7 | C53: =IF(A53<=('Pay off vs Invest'!$B$2-'Pay off vs Invest'!$B$1)*12,Calculations!B53*(1+#REF!/12)^(('Pay off vs Invest'!$B$2-'Pay off vs Invest'!$B$1)*12-A53),0) -> 0 | E53: =C53/((1+#REF!/12)^((('Pay off vs Invest'!$B$2-'Pay off vs Invest'!$B$1)*12)-Calculations!A53)) -> #REF!
A54: =A53+1 -> 53 | B54: =B53 -> 10248.7 | C54: =IF(A54<=('Pay off vs Invest'!$B$2-'Pay off vs Invest'!$B$1)*12,Calculations!B54*(1+#REF!/12)^(('Pay off vs Invest'!$B$2-'Pay off vs Invest'!$B$1)*12-A54),0) -> 0 | E54: =C54/((1+#REF!/12)^((('Pay off vs Invest'!$B$2-'Pay off vs Invest'!$B$1)*12)-Calculations!A54)) -> #REF!
A55: =A54+1 -> 54 | B55: =B54 -> 10248.7 | C55: =IF(A55<=('Pay off vs Invest'!$B$2-'Pay off vs Invest'!$B$1)*12,Calculations!B55*(1+#REF!/12)^(('Pay off vs Invest'!$B$2-'Pay off vs Invest'!$B$1)*12-A55),0) -> 0 | E55: =C55/((1+#REF!/12)^((('Pay off vs Invest'!$B$2-'Pay off vs Invest'!$B$1)*12)-Calculations!A55)) -> #REF!
A56: =A55+1 -> 55 | B56: =B55 -> 10248.7 | C56: =IF(A56<=('Pay off vs Invest'!$B$2-'Pay off vs Invest'!$B$1)*12,Calculations!B56*(1+#REF!/12)^(('Pay off vs Invest'!$B$2-'Pay off vs Invest'!$B$1)*12-A56),0) -> 0 | E56: =C56/((1+#REF!/12)^((('Pay off vs Invest'!$B$2-'Pay off vs Invest'!$B$1)*12)-Calculations!A56)) -> #REF!
A57: =A56+1 -> 56 | B57: =B56 -> 10248.7 | C57: =IF(A57<=('Pay off vs Invest'!$B$2-'Pay off vs Invest'!$B$1)*12,Calculations!B57*(1+#REF!/12)^(('Pay off vs Invest'!$B$2-'Pay off vs Invest'!$B$1)*12-A57),0) -> 0 | E57: =C57/((1+#REF!/12)^((('Pay off vs Invest'!$B$2-'Pay off vs Invest'!$B$1)*12)-Calculations!A57)) -> #REF!
A58: =A57+1 -> 57 | B58: =B57 -> 10248.7 | C58: =IF(A58<=('Pay off vs Invest'!$B$2-'Pay off vs Invest'!$B$1)*12,Calculations!B58*(1+#REF!/12)^(('Pay off vs Invest'!$B$2-'Pay off vs Invest'!$B$1)*12-A58),0) -> 0 | E58: =C58/((1+#REF!/12)^((('Pay off vs Invest'!$B$2-'Pay off vs Invest'!$B$1)*12)-Calculations!A58)) -> #REF!
A59: =A58+1 -> 58 | B59: =B58 -> 10248.7 | C59: =IF(A59<=('Pay off vs Invest'!$B$2-'Pay off vs Invest'!$B$1)*12,Calculations!B59*(1+#REF!/12)^(('Pay off vs Invest'!$B$2-'Pay off vs Invest'!$B$1)*12-A59),0) -> 0 | E59: =C59/((1+#REF!/12)^((('Pay off vs Invest'!$B$2-'Pay off vs Invest'!$B$1)*12)-Calculations!A59)) -> #REF!
A60: =A59+1 -> 59 | B60: =B59 -> 10248.7 | C60: =IF(A60<=('Pay off vs Invest'!$B$2-'Pay off vs Invest'!$B$1)*12,Calculations!B60*(1+#REF!/12)^(('Pay off vs Invest'!$B$2-'Pay off vs Invest'!$B$1)*12-A60),0) -> 0 | E60: =C60/((1+#REF!/12)^((('Pay off vs Invest'!$B$2-'Pay off vs Invest'!$B$1)*12)-Calculations!A60)) -> #REF!
A61: =A60+1 -> 60 | B61: =B60 -> 10248.7 | C61: =IF(A61<=('Pay off vs Invest'!$B$2-'Pay off vs Invest'!$B$1)*12,Calculations!B61*(1+#REF!/12)^(('Pay off vs Invest'!$B$2-'Pay off vs Invest'!$B$1)*12-A61),0) -> 0 | E61: =C61/((1+#REF!/12)^((('Pay off vs Invest'!$B$2-'Pay off vs Invest'!$B$1)*12)-Calculations!A61)) -> #REF!
A62: =A61+1 -> 61 | B62: =B61*(1+'Pay off vs Invest'!$B$7) -> 11273.57 | C62: =IF(A62<=('Pay off vs Invest'!$B$2-'Pay off vs Invest'!$B$1)*12,Calculations!B62*(1+#REF!/12)^(('Pay off vs Invest'!$B$2-'Pay off vs Invest'!$B$1)*12-A62),0) -> 0 | E62: =C62/((1+#REF!/12)^((('Pay off vs Invest'!$B$2-'Pay off vs Invest'!$B$1)*12)-Calculations!A62)) -> #REF!
A63: =A62+1 -> 62 | B63: =B62 -> 11273.57 | C63: =IF(A63<=('Pay off vs Invest'!$B$2-'Pay off vs Invest'!$B$1)*12,Calculations!B63*(1+#REF!/12)^(('Pay off vs Invest'!$B$2-'Pay off vs Invest'!$B$1)*12-A63),0) -> 0 | E63: =C63/((1+#REF!/12)^((('Pay off vs Invest'!$B$2-'Pay off vs Invest'!$B$1)*12)-Calculations!A63)) -> #REF!
A64: =A63+1 -> 63 | B64: =B63 -> 11273.57 | C64: =IF(A64<=('Pay off vs Invest'!$B$2-'Pay off vs Invest'!$B$1)*12,Calculations!B64*(1+#REF!/12)^(('Pay off vs Invest'!$B$2-'Pay off vs Invest'!$B$1)*12-A64),0) -> 0 | E64: =C64/((1+#REF!/12)^((('Pay off vs Invest'!$B$2-'Pay off vs Invest'!$B$1)*12)-Calculations!A64)) -> #REF!
A65: =A64+1 -> 64 | B65: =B64 -> 11273.57 | C65: =IF(A65<=('Pay off vs Invest'!$B$2-'Pay off vs Invest'!$B$1)*12,Calculations!B65*(1+#REF!/12)^(('Pay off vs Invest'!$B$2-'Pay off vs Invest'!$B$1)*12-A65),0) -> 0 | E65: =C65/((1+#REF!/12)^((('Pay off vs Invest'!$B$2-'Pay off vs Invest'!$B$1)*12)-Calculations!A65)) -> #REF!
A66: =A65+1 -> 65 | B66: =B65 -> 11273.57 | C66: =IF(A66<=('Pay off vs Invest'!$B$2-'Pay off vs Invest'!$B$1)*12,Calculations!B66*(1+#REF!/12)^(('Pay off vs Invest'!$B$2-'Pay off vs Invest'!$B$1)*12-A66),0) -> 0 | E66: =C66/((1+#REF!/12)^((('Pay off vs Invest'!$B$2-'Pay off vs Invest'!$B$1)*12)-Calculations!A66)) -> #REF!
A67: =A66+1 -> 66 | B67: =B66 -> 11273.57 | C67: =IF(A67<=('Pay off vs Invest'!$B$2-'Pay off vs Invest'!$B$1)*12,Calculations!B67*(1+#REF!/12)^(('Pay off vs Invest'!$B$2-'Pay off vs Invest'!$B$1)*12-A67),0) -> 0 | E67: =C67/((1+#REF!/12)^((('Pay off vs Invest'!$B$2-'Pay off vs Invest'!$B$1)*12)-Calculations!A67)) -> #REF!
A68: =A67+1 -> 67 | B68: =B67 -> 11273.57 | C68: =IF(A68<=('Pay off vs Invest'!$B$2-'Pay off vs Invest'!$B$1)*12,Calculations!B68*(1+#REF!/12)^(('Pay off vs Invest'!$B$2-'Pay off vs Invest'!$B$1)*12-A68),0) -> 0 | E68: =C68/((1+#REF!/12)^((('Pay off vs Invest'!$B$2-'Pay off vs Invest'!$B$1)*12)-Calculations!A68)) -> #REF!
A69: =A68+1 -> 68 | B69: =B68 -> 11273.57 | C69: =IF(A69<=('Pay off vs Invest'!$B$2-'Pay off vs Invest'!$B$1)*12,Calculations!B69*(1+#REF!/12)^(('Pay off vs Invest'!$B$2-'Pay off vs Invest'!$B$1)*12-A69),0) -> 0 | E69: =C69/((1+#REF!/12)^((('Pay off vs Invest'!$B$2-'Pay off vs Invest'!$B$1)*12)-Calculations!A69)) -> #REF!
A70: =A69+1 -> 69 | B70: =B69 -> 11273.57 | C70: =IF(A70<=('Pay off vs Invest'!$B$2-'Pay off vs Invest'!$B$1)*12,Calculations!B70*(1+#REF!/12)^(('Pay off vs Invest'!$B$2-'Pay off vs Invest'!$B$1)*12-A70),0) -> 0 | E70: =C70/((1+#REF!/12)^((('Pay off vs Invest'!$B$2-'Pay off vs Invest'!$B$1)*12)-Calculations!A70)) -> #REF!
A71: =A70+1 -> 70 | B71: =B70 -> 11273.57 | C71: =IF(A71<=('Pay off vs Invest'!$B$2-'Pay off vs Invest'!$B$1)*12,Calculations!B71*(1+#REF!/12)^(('Pay off vs Invest'!$B$2-'Pay off vs Invest'!$B$1)*12-A71),0) -> 0 | E71: =C71/((1+#REF!/12)^((('Pay off vs Invest'!$B$2-'Pay off vs Invest'!$B$1)*12)-Calculations!A71)) -> #REF!
A72: =A71+1 -> 71 | B72: =B71 -> 11273.57 | C72: =IF(A72<=('Pay off vs Invest'!$B$2-'Pay off vs Invest'!$B$1)*12,Calculations!B72*(1+#REF!/12)^(('Pay off vs Invest'!$B$2-'Pay off vs Invest'!$B$1)*12-A72),0) -> 0 | E72: =C72/((1+#REF!/12)^((('Pay off vs Invest'!$B$2-'Pay off vs Invest'!$B$1)*12)-Calculations!A72)) -> #REF!
A73: =A72+1 -> 72 | B73: =B72 -> 11273.57 | C73: =IF(A73<=('Pay off vs Invest'!$B$2-'Pay off vs Invest'!$B$1)*12,Calculations!B73*(1+#REF!/12)^(('Pay off vs Invest'!$B$2-'Pay off vs Invest'!$B$1)*12-A73),0) -> 0 | E73: =C73/((1+#REF!/12)^((('Pay off vs Invest'!$B$2-'Pay off vs Invest'!$B$1)*12)-Calculations!A73)) -> #REF!
A74: =A73+1 -> 73 | B74: =B73*(1+'Pay off vs Invest'!$B$7) -> 12400.927 | C74: =IF(A74<=('Pay off vs Invest'!$B$2-'Pay off vs Invest'!$B$1)*12,Calculations!B74*(1+#REF!/12)^(('Pay off vs Invest'!$B$2-'Pay off vs Invest'!$B$1)*12-A74),0) -> 0 | E74: =C74/((1+#REF!/12)^((('Pay off vs Invest'!$B$2-'Pay off vs Invest'!$B$1)*12)-Calculations!A74)) -> #REF!
A75: =A74+1 -> 74 | B75: =B74 -> 12400.927 | C75: =IF(A75<=('Pay off vs Invest'!$B$2-'Pay off vs Invest'!$B$1)*12,Calculations!B75*(1+#REF!/12)^(('Pay off vs Invest'!$B$2-'Pay off vs Invest'!$B$1)*12-A75),0) -> 0 | E75: =C75/((1+#REF!/12)^((('Pay off vs Invest'!$B$2-'Pay off vs Invest'!$B$1)*12)-Calculations!A75)) -> #REF!
A76: =A75+1 -> 75 | B76: =B75 -> 12400.927 | C76: =IF(A76<=('Pay off vs Invest'!$B$2-'Pay off vs Invest'!$B$1)*12,Calculations!B76*(1+#REF!/12)^(('Pay off vs Invest'!$B$2-'Pay off vs Invest'!$B$1)*12-A76),0) -> 0 | E76: =C76/((1+#REF!/12)^((('Pay off vs Invest'!$B$2-'Pay off vs Invest'!$B$1)*12)-Calculations!A76)) -> #REF!
A77: =A76+1 -> 76 | B77: =B76 -> 12400.927 | C77: =IF(A77<=('Pay off vs Invest'!$B$2-'Pay off vs Invest'!$B$1)*12,Calculations!B77*(1+#REF!/12)^(('Pay off vs Invest'!$B$2-'Pay off vs Invest'!$B$1)*12-A77),0) -> 0 | E77: =C77/((1+#REF!/12)^((('Pay off vs Invest'!$B$2-'Pay off vs Invest'!$B$1)*12)-Calculations!A77)) -> #REF!
A78: =A77+1 -> 77 | B78: =B77 -> 12400.927 | C78: =IF(A78<=('Pay off vs Invest'!$B$2-'Pay off vs Invest'!$B$1)*12,Calculations!B78*(1+#REF!/12)^(('Pay off vs Invest'!$B$2-'Pay off vs Invest'!$B$1)*12-A78),0) -> 0 | E78: =C78/((1+#REF!/12)^((('Pay off vs Invest'!$B$2-'Pay off vs Invest'!$B$1)*12)-Calculations!A78)) -> #REF!
A79: =A78+1 -> 78 | B79: =B78 -> 12400.927 | C79: =IF(A79<=('Pay off vs Invest'!$B$2-'Pay off vs Invest'!$B$1)*12,Calculations!B79*(1+#REF!/12)^(('Pay off vs Invest'!$B$2-'Pay off vs Invest'!$B$1)*12-A79),0) -> 0 | E79: =C79/((1+#REF!/12)^((('Pay off vs Invest'!$B$2-'Pay off vs Invest'!$B$1)*12)-Calculations!A79)) -> #REF!
A80: =A79+1 -> 79 | B80: =B79 -> 12400.927 | C80: =IF(A80<=('Pay off vs Invest'!$B$2-'Pay off vs Invest'!$B$1)*12,Calculations!B80*(1+#REF!/12)^(('Pay off vs Invest'!$B$2-'Pay off vs Invest'!$B$1)*12-A80),0) -> 0 | E80: =C80/((1+#REF!/12)^((('Pay off vs Invest'!$B$2-'Pay off vs Invest'!$B$1)*12)-Calculations!A80)) -> #REF!
A81: =A80+1 -> 80 | B81: =B80 -> 12400.927 | C81: =IF(A81<=('Pay off vs Invest'!$B$2-'Pay off vs Invest'!$B$1)*12,Calculations!B81*(1+#REF!/12)^(('Pay off vs Invest'!$B$2-'Pay off vs Invest'!$B$1)*12-A81),0) -> 0 | E81: =C81/((1+#REF!/12)^((('Pay off vs Invest'!$B$2-'Pay off vs Invest'!$B$1)*12)-Calculations!A81)) -> #REF!
A82: =A81+1 -> 81 | B82: =B81 -> 12400.927 | C82: =IF(A82<=('Pay off vs Invest'!$B$2-'Pay off vs Invest'!$B$1)*12,Calculations!B82*(1+#REF!/12)^(('Pay off vs Invest'!$B$2-'Pay off vs Invest'!$B$1)*12-A82),0) -> 0 | E82: =C82/((1+#REF!/12)^((('Pay off vs Invest'!$B$2-'Pay off vs Invest'!$B$1)*12)-Calculations!A82)) -> #REF!
A83: =A82+1 -> 82 | B83: =B82 -> 12400.927 | C83: =IF(A83<=('Pay off vs Invest'!$B$2-'Pay off vs Invest'!$B$1)*12,Calculations!B83*(1+#REF!/12)^(('Pay off vs Invest'!$B$2-'Pay off vs Invest'!$B$1)*12-A83),0) -> 0 | E83: =C83/((1+#REF!/12)^((('Pay off vs Invest'!$B$2-'Pay off vs Invest'!$B$1)*12)-Calculations!A83)) -> #REF!
A84: =A83+1 -> 83 | B84: =B83 -> 12400.927 | C84: =IF(A84<=('Pay off vs Invest'!$B$2-'Pay off vs Invest'!$B$1)*12,Calculations!B84*(1+#REF!/12)^(('Pay off vs Invest'!$B$2-'Pay off vs Invest'!$B$1)*12-A84),0) -> 0 | E84: =C84/((1+#REF!/12)^((('Pay off vs Invest'!$B$2-'Pay off vs Invest'!$B$1)*12)-Calculations!A84)) -> #REF!
A85: =A84+1 -> 84 | B85: =B84 -> 12400.927 | C85: =IF(A85<=('Pay off vs Invest'!$B$2-'Pay off vs Invest'!$B$1)*12,Calculations!B85*(1+#REF!/12)^(('Pay off vs Invest'!$B$2-'Pay off vs Invest'!$B$1)*12-A85),0) -> 0 | E85: =C85/((1+#REF!/12)^((('Pay off vs Invest'!$B$2-'Pay off vs Invest'!$B$1)*12)-Calculations!A85)) -> #REF!
A86: =A85+1 -> 85 | B86: =B85*(1+'Pay off vs Invest'!$B$7) -> 13641.02 | C86: =IF(A86<=('Pay off vs Invest'!$B$2-'Pay off vs Invest'!$B$1)*12,Calculations!B86*(1+#REF!/12)^(('Pay off vs Invest'!$B$2-'Pay off vs Invest'!$B$1)*12-A86),0) -> 0 | E86: =C86/((1+#REF!/12)^((('Pay off vs Invest'!$B$2-'Pay off vs Invest'!$B$1)*12)-Calculations!A86)) -> #REF!
A87: =A86+1 -> 86 | B87: =B86 -> 13641.02 | C87: =IF(A87<=('Pay off vs Invest'!$B$2-'Pay off vs Invest'!$B$1)*12,Calculations!B87*(1+#REF!/12)^(('Pay off vs Invest'!$B$2-'Pay off vs Invest'!$B$1)*12-A87),0) -> 0 | E87: =C87/((1+#REF!/12)^((('Pay off vs Invest'!$B$2-'Pay off vs Invest'!$B$1)*12)-Calculations!A87)) -> #REF!
A88: =A87+1 -> 87 | B88: =B87 -> 13641.02 | C88: =IF(A88<=('Pay off vs Invest'!$B$2-'Pay off vs Invest'!$B$1)*12,Calculations!B88*(1+#REF!/12)^(('Pay off vs Invest'!$B$2-'Pay off vs Invest'!$B$1)*12-A88),0) -> 0 | E88: =C88/((1+#REF!/12)^((('Pay off vs Invest'!$B$2-'Pay off vs Invest'!$B$1)*12)-Calculations!A88)) -> #REF!
A89: =A88+1 -> 88 | B89: =B88 -> 13641.02 | C89: =IF(A89<=('Pay off vs Invest'!$B$2-'Pay off vs Invest'!$B$1)*12,Calculations!B89*(1+#REF!/12)^(('Pay off vs Invest'!$B$2-'Pay off vs Invest'!$B$1)*12-A89),0) -> 0 | E89: =C89/((1+#REF!/12)^((('Pay off vs Invest'!$B$2-'Pay off vs Invest'!$B$1)*12)-Calculations!A89)) -> #REF!
A90: =A89+1 -> 89 | B90: =B89 -> 13641.02 | C90: =IF(A90<=('Pay off vs Invest'!$B$2-'Pay off vs Invest'!$B$1)*12,Calculations!B90*(1+#REF!/12)^(('Pay off vs Invest'!$B$2-'Pay off vs Invest'!$B$1)*12-A90),0) -> 0 | E90: =C90/((1+#REF!/12)^((('Pay off vs Invest'!$B$2-'Pay off vs Invest'!$B$1)*12)-Calculations!A90)) -> #REF!
A91: =A90+1 -> 90 | B91: =B90 -> 13641.02 | C91: =IF(A91<=('Pay off vs Invest'!$B$2-'Pay off vs Invest'!$B$1)*12,Calculations!B91*(1+#REF!/12)^(('Pay off vs Invest'!$B$2-'Pay off vs Invest'!$B$1)*12-A91),0) -> 0 | E91: =C91/((1+#REF!/12)^((('Pay off vs Invest'!$B$2-'Pay off vs Invest'!$B$1)*12)-Calculations!A91)) -> #REF!
A92: =A91+1 -> 91 | B92: =B91 -> 13641.02 | C92: =IF(A92<=('Pay off vs Invest'!$B$2-'Pay off vs Invest'!$B$1)*12,Calculations!B92*(1+#REF!/12)^(('Pay off vs Invest'!$B$2-'Pay off vs Invest'!$B$1)*12-A92),0) -> 0 | E92: =C92/((1+#REF!/12)^((('Pay off vs Invest'!$B$2-'Pay off vs Invest'!$B$1)*12)-Calculations!A92)) -> #REF!
A93: =A92+1 -> 92 | B93: =B92 -> 13641.02 | C93: =IF(A93<=('Pay off vs Invest'!$B$2-'Pay off vs Invest'!$B$1)*12,Calculations!B93*(1+#REF!/12)^(('Pay off vs Invest'!$B$2-'Pay off vs Invest'!$B$1)*12-A93),0) -> 0 | E93: =C93/((1+#REF!/12)^((('Pay off vs Invest'!$B$2-'Pay off vs Invest'!$B$1)*12)-Calculations!A93)) -> #REF!
A94: =A93+1 -> 93 | B94: =B93 -> 13641.02 | C94: =IF(A94<=('Pay off vs Invest'!$B$2-'Pay off vs Invest'!$B$1)*12,Calculations!B94*(1+#REF!/12)^(('Pay off vs Invest'!$B$2-'Pay off vs Invest'!$B$1)*12-A94),0) -> 0 | E94: =C94/((1+#REF!/12)^((('Pay off vs Invest'!$B$2-'Pay off vs Invest'!$B$1)*12)-Calculations!A94)) -> #REF!
A95: =A94+1 -> 94 | B95: =B94 -> 13641.02 | C95: =IF(A95<=('Pay off vs Invest'!$B$2-'Pay off vs Invest'!$B$1)*12,Calculations!B95*(1+#REF!/12)^(('Pay off vs Invest'!$B$2-'Pay off vs Invest'!$B$1)*12-A95),0) -> 0 | E95: =C95/((1+#REF!/12)^((('Pay off vs Invest'!$B$2-'Pay off vs Invest'!$B$1)*12)-Calculations!A95)) -> #REF!
A96: =A95+1 -> 95 | B96: =B95 -> 13641.02 | C96: =IF(A96<=('Pay off vs Invest'!$B$2-'Pay off vs Invest'!$B$1)*12,Calculations!B96*(1+#REF!/12)^(('Pay off vs Invest'!$B$2-'Pay off vs Invest'!$B$1)*12-A96),0) -> 0 | E96: =C96/((1+#REF!/12)^((('Pay off vs Invest'!$B$2-'Pay off vs Invest'!$B$1)*12)-Calculations!A96)) -> #REF!
A97: =A96+1 -> 96 | B97: =B96 -> 13641.02 | C97: =IF(A97<=('Pay off vs Invest'!$B$2-'Pay off vs Invest'!$B$1)*12,Calculations!B97*(1+#REF!/12)^(('Pay off vs Invest'!$B$2-'Pay off vs Invest'!$B$1)*12-A97),0) -> 0 | E97: =C97/((1+#REF!/12)^((('Pay off vs Invest'!$B$2-'Pay off vs Invest'!$B$1)*12)-Calculations!A97)) -> #REF!
A98: =A97+1 -> 97 | B98: =B97*(1+'Pay off vs Invest'!$B$7) -> 15005.122 | C98: =IF(A98<=('Pay off vs Invest'!$B$2-'Pay off vs Invest'!$B$1)*12,Calculations!B98*(1+#REF!/12)^(('Pay off vs Invest'!$B$2-'Pay off vs Invest'!$B$1)*12-A98),0) -> 0 | E98: =C98/((1+#REF!/12)^((('Pay off vs Invest'!$B$2-'Pay off vs Invest'!$B$1)*12)-Calculations!A98)) -> #REF!
A99: =A98+1 -> 98 | B99: =B98 -> 15005.122 | C99: =IF(A99<=('Pay off vs Invest'!$B$2-'Pay off vs Invest'!$B$1)*12,Calculations!B99*(1+#REF!/12)^(('Pay off vs Invest'!$B$2-'Pay off vs Invest'!$B$1)*12-A99),0) -> 0 | E99: =C99/((1+#REF!/12)^((('Pay off vs Invest'!$B$2-'Pay off vs Invest'!$B$1)*12)-Calculations!A99)) -> #REF!
A100: =A99+1 -> 99 | B100: =B99 -> 15005.122 | C100: =IF(A100<=('Pay off vs Invest'!$B$2-'Pay off vs Invest'!$B$1)*12,Calculations!B100*(1+#REF!/12)^(('Pay off vs Invest'!$B$2-'Pay off vs Invest'!$B$1)*12-A100),0) -> 0 | E100: =C100/((1+#REF!/12)^((('Pay off vs Invest'!$B$2-'Pay off vs Invest'!$B$1)*12)-Calculations!A100)) -> #REF!
...
